tests/__init__.py
tox_test_command/__init__.py
tox_test_command/command.py
bernardomg.tox_test_command-1.2.0.dist-info/LICENSE
bernardomg.tox_test_command-1.2.0.dist-info/METADATA
bernardomg.tox_test_command-1.2.0.dist-info/WHEEL
bernardomg.tox_test_command-1.2.0.dist-info/top_level.txt
bernardomg.tox_test_command-1.2.0.dist-info/RECORD
