Metadata-Version: 2.1
Name: bernardomg.tox-test-command
Version: 1.2.0
Summary: setuptools command for running tests using tox
Home-page: https://github.com/Bernardo-MG/tox-test-command
Author: Bernardo MartÃ­nez Garrido
Author-email: programming@bernardomg.com
License: MIT
Download-URL: https://pypi.python.org/pypi/bernardomg.tox-test-command
Platform: any
Classifier: Development Status :: 5 - Production/Stable
Classifier: License :: OSI Approved :: MIT License
Classifier: Programming Language :: Python
Classifier: Programming Language :: Python :: 3
Classifier: Programming Language :: Python :: 3.6
Classifier: Programming Language :: Python :: 3.7
Classifier: Programming Language :: Python :: 3.8
Classifier: Programming Language :: Python :: 3.9
Requires-Dist: setuptools
Requires-Dist: tox
Provides-Extra: test
Requires-Dist: tox ; extra == 'test'
